hashlib_additional/__init__.py
tests/__init__.py
tests/test_hashlib_additional.py
hashlib_additional-1.1.dist-info/METADATA
hashlib_additional-1.1.dist-info/WHEEL
hashlib_additional-1.1.dist-info/top_level.txt
hashlib_additional-1.1.dist-info/RECORD
