Metadata-Version: 2.1
Name: hashlib-additional
Version: 1.1
Summary: Additional hashlib-compatible hashing digests
Home-page: https://github.com/rfinnie/python-hashlib-additional
Author: Ryan Finnie
Author-email: ryan@finnie.org
License: BSD
Download-URL: https://github.com/rfinnie/python-hashlib-additional
Platform: Unix
Classifier: Development Status :: 5 - Production/Stable
Classifier: Intended Audience :: Developers
Classifier: License :: OSI Approved :: BSD License
Classifier: Programming Language :: Python :: 3 :: Only
Classifier: Programming Language :: Python :: Implementation :: PyPy
Classifier: Topic :: Software Development :: Libraries :: Python Modules
